pykinosh/__init__.py
pykinosh/core.py
pykinosh-0.1.5.dist-info/LICENSE.md
pykinosh-0.1.5.dist-info/METADATA
pykinosh-0.1.5.dist-info/WHEEL
pykinosh-0.1.5.dist-info/top_level.txt
pykinosh-0.1.5.dist-info/RECORD
